Workbook

Sheet Members
A1: Member Name | B1: Email Id | C1: Phone Number
A2: Kothacheruvu Anil Kumar Reddy | B2: anil.kothacheruvu@gmail.com | C2: +44 7405826322
A3: Chittiboyina Ramanjaneyulu | B3: anjimca48@gmail.com | C3: +1 4379914275
A4: Chintalapalli Srinith | B4: srimca67@gmail.com | C4: +49 15145257581
A5: Rallabandi Venkata Narasimha Charlu | B5: venkat.0082@gmail.com | C5: +91 9703973857
A6: Bhagavan Das | B6: bagavandas.g@gmail.com
A7: Jetty Harikrishna Krishna | B7: hkjetti@gmail.com | C7: +61 410013839
A8: Darisiguntla Lakshmi Narayana | B8: dlnarayana.mca29@gmail.com | C8: +91 7337247237
A9: Chindukuri Mallikarjuna | B9: malli.chindukuri@gmail.com | C9: +91 8096069176
A10: Malli Sunil Kumar | B10: mallisunilmca69@gmail.com | C10: +91 8885359545
A11: Korrakuti Paramesh | B11: paramesh.java5@gmail.com | C11: +91 9686667810
A12: Ponugoti Prasad | B12: prasadnaidu271985@gmail.com | C12: +91 9611916549
A13: Bollam Samba Siva Reddy | B13: sambamca06@gmail.com | C13: +91 9845584288
A14: Biddala Sandeep Kumar Reddy | B14: sandeep.mca56@gmail.com | C14: +1 2484801790
A15: Gopathi Sheshagiri | B15: sheshagiri.gopathi@gmail.com | C15: +91 9885272070
A16: Duggireddy Srinath Reddy | B16: sreemca65@gmail.com | C16: +91 9986717002
A17: Meda Sunil Kumar Reddy | B17: sunilreddy.meda@gmail.com | C17: +91 9742200259
A18: Kollai Venkateswarlu | B18: venky.kollai@gmail.com | C18: +91 9703318047
... A23: Koppavarapu Sudhakar | B23: sudhakar487248@gmail.com | C23: +91 7760055839

Sheet Summary
A1: Contributions | D1: Loans | G1: Donations
A2: Total Contrbuitions | B2: =Contributions!B25-Contributions!B24 -> 880317 | D2: Current Loan Value | E2: =SUM(Loans!M:M) -> 550000 | G2: Donated so far | H2: =SUM(Donations!E:E) -> 145000
A3: Interest Earned (Bank, Loans, etc) | B3: =Contributions!B24 -> 104038 | D3: Bad Debts | E3: =SUM(Loans!N:N) -> 70000
A5: Grand Total | B5: =SUM(B2:B3) -> 984355 | D5: Grand Total | E5: =SUM(E2:E3) -> 620000 | G5: Grand Total | H5: =SUM(H2:H3) -> 145000
A8: Reconcilation
A9: Contributions | B9: =B5 -> 984355
A10: Current Balance | B10: 214349
A11: Loans | B11: =E5 -> 620000
A12: Donations | B12: =H5 -> 145000
A14: Reconcilation Amount | B14: =B9-B10-B11-B12 -> 5006

Sheet Contributions
A1: Name | B1: Total | C1: 2016 | D1: 2017 | E1: 2018 | F1: 2019 | G1: 2020 | H1: 2021 | I1: 2022 | J1: 2023 | K1: 2024 | L1: 2025 | M1: 2026
A2: Kothacheruvu Anil Kumar Reddy | B2: =SUM(C2:X2) -> 59000 | C2: ='2016'!H2 -> 8000 | D2: ='2017'!N2 -> 8500 | E2: ='2018'!N2 -> 6000 | F2: ='2019'!N2 -> 6000 | G2: ='2020'!N2 -> 5500 | H2: ='2021'!N2 -> 4500 | I2: ='2022'!N2 -> 500 | J2: ='2023'!N2 -> 1500 | K2: ='2024'!N2 -> 6000 | L2: ='2025'!N2 -> 10000 | M2: ='2026'!N2 -> 2500
A3: Chittiboyina Ramanjaneyulu | B3: =SUM(C3:X3) -> 44000 | C3: ='2016'!H3 -> 3500 | D3: ='2017'!N3 -> 6000 | E3: ='2018'!N3 -> 4500 | F3: ='2019'!N3 -> 0 | G3: ='2020'!N3 -> 4000 | H3: ='2021'!N3 -> 4500 | I3: ='2022'!N3 -> 1500 | J3: ='2023'!N3 -> 3000 | K3: ='2024'!N3 -> 1000 | L3: ='2025'!N3 -> 16000 | M3: ='2026'!N3 -> 0
A4: Chintalapalli Srinith | B4: =SUM(C4:X4) -> 59000 | C4: ='2016'!H4 -> 3500 | D4: ='2017'!N4 -> 6000 | E4: ='2018'!N4 -> 6000 | F4: ='2019'!N4 -> 6000 | G4: ='2020'!N4 -> 6000 | H4: ='2021'!N4 -> 6000 | I4: ='2022'!N4 -> 5500 | J4: ='2023'!N4 -> 5500 | K4: ='2024'!N4 -> 6000 | L4: ='2025'!N4 -> 6000 | M4: ='2026'!N4 -> 2500
A5: Rallabandi Venkata Narasimha Charlu | B5: =SUM(C5:X5) -> 57500 | C5: ='2016'!H5 -> 4000 | D5: ='2017'!N5 -> 11000 | E5: ='2018'!N5 -> 10500 | F5: ='2019'!N5 -> 3000 | G5: ='2020'!N5 -> 3000 | H5: ='2021'!N5 -> 6000 | I5: ='2022'!N5 -> 2500 | J5: ='2023'!N5 -> 4000 | K5: ='2024'!N5 -> 5500 | L5: ='2025'!N5 -> 5500 | M5: ='2026'!N5 -> 2500
A6: Bhagavan Das | B6: =SUM(C6:X6) -> 20500 | C6: ='2016'!H6 -> 6000 | D6: ='2017'!N6 -> 3000 | E6: ='2018'!N6 -> 0 | F6: ='2019'!N6 -> 0 | G6: ='2020'!N6 -> 4000 | H6: ='2021'!N6 -> 5000 | I6: ='2022'!N6 -> 2500 | J6: ='2023'!N6 -> 0 | K6: ='2024'!N6 -> 0 | L6: ='2025'!N6 -> 0 | M6: ='2026'!N6 -> 0
A7: Jetty Harikrishna Krishna | B7: =SUM(C7:X7) -> 27500 | C7: ='2016'!H7 -> 4500 | D7: ='2017'!N7 -> 9000 | E7: ='2018'!N7 -> 5000 | F7: ='2019'!N7 -> 3000 | G7: ='2020'!N7 -> 6000 | H7: ='2021'!N7 -> 0 | I7: ='2022'!N7 -> 0 | J7: ='2023'!N7 -> 0 | K7: ='2024'!N7 -> 0 | L7: ='2025'!N7 -> 0 | M7: ='2026'!N7 -> 0
A8: Darisiguntla Lakshmi Narayana | B8: =SUM(C8:X8) -> 57900 | C8: ='2016'!H8 -> 5000 | D8: ='2017'!N8 -> 3500 | E8: ='2018'!N8 -> 5000 | F8: ='2019'!N8 -> 4500 | G8: ='2020'!N8 -> 6900 | H8: ='2021'!N8 -> 5800 | I8: ='2022'!N8 -> 7000 | J8: ='2023'!N8 -> 6000 | K8: ='2024'!N8 -> 3500 | L8: ='2025'!N8 -> 6950 | M8: ='2026'!N8 -> 3750
A9: Chindukuri Mallikarjuna | B9: =SUM(C9:X9) -> 36050 | C9: ='2016'!H9 -> 3500 | D9: ='2017'!N9 -> 6050 | E9: ='2018'!N9 -> 6000 | F9: ='2019'!N9 -> 6500 | G9: ='2020'!N9 -> 5000 | H9: ='2021'!N9 -> 6000 | I9: ='2022'!N9 -> 2000 | J9: ='2023'!N9 -> 0 | K9: ='2024'!N9 -> 0 | L9: ='2025'!N9 -> 1000 | M9: ='2026'!N9 -> 0
A10: Malli Sunil Kumar | B10: =SUM(C10:X10) -> 16000 | C10: ='2016'!H10 -> 4000 | D10: ='2017'!N10 -> 4000 | E10: ='2018'!N10 -> 3000 | F10: ='2019'!N10 -> 5000 | G10: ='2020'!N10 -> 0 | H10: ='2021'!N10 -> 0 | I10: ='2022'!N10 -> 0 | J10: ='2023'!N10 -> 0 | K10: ='2024'!N10 -> 0 | L10: ='2025'!N10 -> 0 | M10: ='2026'!N10 -> 0
A11: Korrakuti Paramesh | B11: =SUM(C11:X11) -> 59000 | C11: ='2016'!H11 -> 3500 | D11: ='2017'!N11 -> 6000 | E11: ='2018'!N11 -> 6000 | F11: ='2019'!N11 -> 6000 | G11: ='2020'!N11 -> 6000 | H11: ='2021'!N11 -> 6000 | I11: ='2022'!N11 -> 5500 | J11: ='2023'!N11 -> 5500 | K11: ='2024'!N11 -> 6000 | L11: ='2025'!N11 -> 6000 | M11: ='2026'!N11 -> 2500
A12: Ponugoti Prasad | B12: =SUM(C12:X12) -> 60560 | C12: ='2016'!H12 -> 3500 | D12: ='2017'!N12 -> 6000 | E12: ='2018'!N12 -> 6000 | F12: ='2019'!N12 -> 0 | G12: ='2020'!N12 -> 12000 | H12: ='2021'!N12 -> 6000 | I12: ='2022'!N12 -> 5500 | J12: ='2023'!N12 -> 5500 | K12: ='2024'!N12 -> 5000 | L12: ='2025'!N12 -> 7310 | M12: ='2026'!N12 -> 3750
A13: Bollam Samba Siva Reddy | B13: =SUM(C13:X13) -> 42801 | C13: ='2016'!H13 -> 3500 | D13: ='2017'!N13 -> 6000 | E13: ='2018'!N13 -> 5500 | F13: ='2019'!N13 -> 2000 | G13: ='2020'!N13 -> 2000 | H13: ='2021'!N13 -> 1000 | I13: ='2022'!N13 -> 5000 | J13: ='2023'!N13 -> 2500 | K13: ='2024'!N13 -> 6300 | L13: ='2025'!N13 -> 7501 | M13: ='2026'!N13 -> 1500
... A23: Koppavarapu Sudhakar | B23: =SUM(C23:X23) -> 25001 | C23: ='2016'!H23 -> 0 | D23: ='2017'!N23 -> 0 | E23: ='2018'!N23 -> 0 | F23: ='2019'!N23 -> 0 | G23: ='2020'!N23 -> 1000 | H23: ='2021'!N23 -> 5000 | I23: ='2022'!N23 -> 4000 | J23: ='2023'!N23 -> 2500 | K23: ='2024'!N23 -> 5000 | L23: ='2025'!N23 -> 5001 | M23: ='2026'!N23 -> 2500
A24: Bank Intrest/M.chit / Loans Interest | B24: =SUM(C24:X24) -> 104038 | C24: ='2016'!H24 -> 704 | D24: ='2017'!N24 -> 3473 | E24: ='2018'!N24 -> 19988 | F24: ='2019'!N24 -> 14203 | G24: ='2020'!N24 -> 11872 | H24: ='2021'!N24 -> 21131 | I24: ='2022'!N20 -> 5500 | J24: ='2023'!N24 -> 3000 | K24: ='2024'!N24 -> 8600 | L24: ='2025'!N24 -> 13264 | M24: ='2026'!N24 -> 2303
A25: Total | B25: =SUM(B2:B24) -> 984355 | C25: =SUM(C2:C24) -> 74704 | D25: =SUM(D2:D24) -> 111023 | E25: =SUM(E2:E24) -> 113988 | F25: =SUM(F2:F24) -> 67203 | G25: =SUM(G2:G24) -> 121277 | H25: =SUM(H2:H24) -> 120831 | I25: =SUM(I2:I24) -> 81100 | ... L25: =SUM(L2:L24) -> 118126 | M25: ='2026'!N26 -> 38203

Sheet Loans
A1: SNO | B1: Name | C1: Amount | D1: Loan Type | E1: Start Date | F1: End Date | G1: Duration | H1: Status | I1: Interest Payable | J1: Interest Paid | K1: Interest Due | L1: Principal Paid | M1: Balance | N1: Bad Debt | O1: Remarks | P1: Active Loan | Q1: =SUMIFS(M2:M103, H2:H103, "<>Write Off") -> 550000
A2: 1 | B2: Bhagavan Das | C2: 80000 | D2: Personal | E2: 44927 | F2: 45661 | G2: =DATEDIF(E2, IF(F2="", TODAY(), F2), "Y") & "Y:" & DATEDIF(E2, IF(F2="", TODAY(), F2), "YM") & "M:" & DATEDIF(E2, IF(F2="", TODAY(), F2), "MD") & "D" -> 2Y:0M:3D | H2: Write Off | J2: 0 | K2: =I2-J2 -> 0 | L2: 10000 | M2: 0 | N2: 70000 | O2: Interest free loan for his business. | P2: Write Offs | Q2: =SUMIFS(M2:M103, H2:H103, "Write Off") -> 0
A3: 2 | B3: Bollam Samba Siva Reddy | C3: 100000 | D3: Personal | E3: 45026 | F3: 45739 | G3: =DATEDIF(E3, IF(F3="", TODAY(), F3), "Y") & "Y:" & DATEDIF(E3, IF(F3="", TODAY(), F3), "YM") & "M:" & DATEDIF(E3, IF(F3="", TODAY(), F3), "MD") & "D" -> 1Y:11M:13D | H3: Paid | K3: =I3-J3 -> 0 | L3: 100000 | M3: =C3-L3 -> 0 | O3: For his financial needs to set up his new home. | P3: Total | Q3: =SUM(Q1:Q2) -> 550000
A4: 3 | B4: Koppavarapu Sudhakar | C4: 100000 | D4: Medical | E4: 44995 | G4: =DATEDIF(E4, IF(F4="", TODAY(), F4), "Y") & "Y:" & DATEDIF(E4, IF(F4="", TODAY(), F4), "YM") & "M:" & DATEDIF(E4, IF(F4="", TODAY(), F4), "MD") & "D" -> 3Y:2M:13D | H4: Paid | K4: =I4-J4 -> 0 | L4: 100000 | M4: =C4-L4 -> 0 | O4: For his mother health expenses.
A5: 4 | B5: Malli Sunil Kumar | C5: 100000 | D5: Personal | G5: =DATEDIF(E5, IF(F5="", TODAY(), F5), "Y") & "Y:" & DATEDIF(E5, IF(F5="", TODAY(), F5), "YM") & "M:" & DATEDIF(E5, IF(F5="", TODAY(), F5), "MD") & "D" -> 126Y:4M:23D | H5: Paid | K5: =I5-J5 -> 0 | L5: 100000 | M5: =C5-L5 -> 0 | O5: Interest free loan for his house construction.
A6: 5 | B6: Korrakuti Paramesh | C6: 100000 | D6: Personal | E6: 45639 | F6: 45662 | G6: =DATEDIF(E6, IF(F6="", TODAY(), F6), "Y") & "Y:" & DATEDIF(E6, IF(F6="", TODAY(), F6), "YM") & "M:" & DATEDIF(E6, IF(F6="", TODAY(), F6), "MD") & "D" -> 0Y:0M:23D | H6: Paid | I6: =(VALUE(LEFT(G6,FIND("Y",G6)-1))*12 + VALUE(MID(G6,FIND(":",G6)+1,FIND("M",G6)-FIND(":",G6)-1))) * 650 -> 0 | J6: 650 | K6: =I6-J6 -> -650 | L6: 100000 | M6: 0 | O6: For buying car
A7: 6 | B7: Chindukuri Mallikarjuna | C7: 100000 | D7: Personal | E7: 45737 | G7: =DATEDIF(E7, IF(F7="", TODAY(), F7), "Y") & "Y:" & DATEDIF(E7, IF(F7="", TODAY(), F7), "YM") & "M:" & DATEDIF(E7, IF(F7="", TODAY(), F7), "MD") & "D" -> 1Y:2M:2D | H7: Active | I7: =(VALUE(LEFT(G7,FIND("Y",G7)-1))*12 + VALUE(MID(G7,FIND(":",G7)+1,FIND("M",G7)-FIND(":",G7)-1))) * 650 -> 9100 | J7: 0 | K7: =I7-J7 -> 9100 | L7: 0 | M7: =C7-L7 -> 100000 | O7: Interest free loan for first 6 months.
A8: 7 | B8: Chintalapalli Srinith | C8: 150000 | D8: Medical | E8: 45689 | G8: =DATEDIF(E8, IF(F8="", TODAY(), F8), "Y") & "Y:" & DATEDIF(E8, IF(F8="", TODAY(), F8), "YM") & "M:" & DATEDIF(E8, IF(F8="", TODAY(), F8), "MD") & "D" -> 1Y:3M:22D | H8: Active | I8: =(VALUE(LEFT(G8,FIND("Y",G8)-1))*12 + VALUE(MID(G8,FIND(":",G8)+1,FIND("M",G8)-FIND(":",G8)-1)) - 12) * 650 -> 1950 | J8: =1300 -> 1300 | K8: =I8-J8 -> 650 | L8: 0 | M8: =C8-L8 -> 150000
A9: 8 | B9: Darisiguntla Lakshmi Narayana | C9: 100000 | D9: Personal | E9: 45776 | G9: =DATEDIF(E9, IF(F9="", TODAY(), F9), "Y") & "Y:" & DATEDIF(E9, IF(F9="", TODAY(), F9), "YM") & "M:" & DATEDIF(E9, IF(F9="", TODAY(), F9), "MD") & "D" -> 1Y:0M:24D | H9: Active | I9: =(VALUE(LEFT(G9,FIND("Y",G9)-1))*12 + VALUE(MID(G9,FIND(":",G9)+1,FIND("M",G9)-FIND(":",G9)-1))) * 650 -> 7800 | J9: =650+650+650+650+650+650+650+650+650+650+650+650 -> 7800 | K9: =I9-J9 -> 0 | L9: 0 | M9: 100000
A10: 9 | B10: Darisiguntla Lakshmi Narayana | C10: 100000 | D10: Personal | E10: 45721 | G10: =DATEDIF(E10, IF(F10="", TODAY(), F10), "Y") & "Y:" & DATEDIF(E10, IF(F10="", TODAY(), F10), "YM") & "M:" & DATEDIF(E10, IF(F10="", TODAY(), F10), "MD") & "D" -> 1Y:2M:18D | H10: Active | I10: =(VALUE(LEFT(G10,FIND("Y",G10)-1))*12 + VALUE(MID(G10,FIND(":",G10)+1,FIND("M",G10)-FIND(":",G10)-1))) * 650 -> 9100 | J10: =650+650+650+650+650+650+650+650+650+650+650+650+650 -> 8450 | K10: =I10-J10 -> 650 | L10: 0 | M10: 100000 | O10: For business reasons
A11: 10 | B11: Meda Sunil Kumar Reddy | C11: 100000 | D11: Personal | E11: 45940 | G11: =DATEDIF(E11, IF(F11="", TODAY(), F11), "Y") & "Y:" & DATEDIF(E11, IF(F11="", TODAY(), F11), "YM") & "M:" & DATEDIF(E11, IF(F11="", TODAY(), F11), "MD") & "D" -> 0Y:7M:13D | H11: Active | I11: =(VALUE(LEFT(G11,FIND("Y",G11)-1))*12 + VALUE(MID(G11,FIND(":",G11)+1,FIND("M",G11)-FIND(":",G11)-1))) * 650 -> 4550 | J11: =800+650+650+650+650+650 -> 4050 | K11: =I11-J11 -> 500 | L11: 0 | M11: 100000 | O11: For persnal reasons
A12: 11 | K12: =I12-J12 -> 0
A13: 12 | K13: =I13-J13 -> 0
A14: 13 | K14: =I14-J14 -> 0
A15: 14 | K15: =I15-J15 -> 0
K16: =I16-J16 -> 0
K17: =I17-J17 -> 0
K18: =I18-J18 -> 0
K19: =I19-J19 -> 0
K20: =I20-J20 -> 0
K21: =I21-J21 -> 0
K22: =I22-J22 -> 0
K23: =I23-J23 -> 0
K24: =I24-J24 -> 0
K25: =I25-J25 -> 0
K26: =I26-J26 -> 0
K27: =I27-J27 -> 0
... K84: =I84-J84 -> 0

Sheet Donations
A1: SNO | B1: Victim Name | C1: Referred By | D1: Date | E1: Amount | F1: Remarks | H1: Total | I1: =SUM(E2:E149) -> 145000
A2: 1 | B2: Bhagavan Das | C2: Self | E2: 30000 | F2: To help his medical issues.
A3: 2 | B3: Naidruva | C3: Lakshmi Narayana | E3: 10000 | F3: To help his medical issues.
A4: 3 | B4: Sampoorna | E4: 30000 | F4: Education
A5: 4 | B5: Jagadeesh | C5: Mallikarjuna | E5: 25000 | F5: To help his medical issues.
A6: 5 | B6: Narasimhulu Oruganti | C6: Anji | E6: 20000 | F6: To help his medical issues.
A7: 7 | B7: Master Harinath | C7: Sunil Malli | E7: 20000 | F7: To help medical issues
A8: 8 | C8: Shesagiri | D8: 45453 | E8: 10000 | F8: To help his medical issues.

Sheet 2026
A1: Name | B1: Jan | C1: Feb | D1: Mar | E1: Apr | F1: May | G1: Jun | H1: July | I1: Aug | J1: Sep | K1: Oct | L1: Nov | M1: Dec | N1: Total
A2: Kothacheruvu Anil Kumar Reddy | B2: 500 | C2: 500 | D2: 500 | E2: 0 | F2: 1000 | N2: =SUM(B2:M2) -> 2500
A3: Chittiboyina Ramanjaneyulu | B3: 0 | C3: 0 | N3: =SUM(B3:M3) -> 0
A4: Chintalapalli Srinith | B4: 500 | C4: 500 | D4: 500 | E4: 0 | F4: 1000 | N4: =SUM(B4:M4) -> 2500
A5: Rallabandi Venkata Narasimha Charlu | B5: 500 | C5: 500 | D5: 500 | E5: 500 | F5: 500 | N5: =SUM(B5:M5) -> 2500
A6: Bhagavan Das | N6: =SUM(B6:M6) -> 0
A7: Jetty Harikrishna Krishna | N7: =SUM(B7:M7) -> 0
A8: Darisiguntla Lakshmi Narayana | B8: 750 | C8: 750 | D8: 750 | E8: 750 | F8: 750 | N8: =SUM(B8:M8) -> 3750
A9: Chindukuri Mallikarjuna | B9: 0 | C9: 0 | D9: 0 | E9: 0 | N9: =SUM(B9:M9) -> 0
A10: Malli Sunil Kumar | N10: =SUM(B10:M10) -> 0
A11: Korrakuti Paramesh | B11: 500 | C11: 500 | D11: 500 | E11: 0 | F11: 1000 | N11: =SUM(B11:M11) -> 2500
A12: Ponugoti Prasad | B12: 750 | C12: 750 | D12: 750 | E12: 750 | F12: 750 | N12: =SUM(B12:M12) -> 3750
A13: Bollam Samba Siva Reddy | B13: 500 | C13: 0 | D13: 0 | F13: 1000 | N13: =SUM(B13:M13) -> 1500
A14: Biddala Sandeep Kumar Reddy | B14: 500 | C14: 500 | D14: 500 | E14: 0 | F14: 1000 | N14: =SUM(B14:M14) -> 2500
A15: Gopathi Sheshagiri | N15: =SUM(B15:M15) -> 0
A16: Duggireddy Srinath Reddy | B16: 500 | C16: 500 | D16: 500 | E16: 500 | F16: 500 | N16: =SUM(B16:M16) -> 2500
A17: Meda Sunil Kumar Reddy | B17: 0 | C17: 500 | D17: 500 | E17: 500 | F17: 500 | N17: =SUM(B17:M17) -> 2000
A18: Kollai Venkateswarlu | B18: 500 | C18: 500 | D18: 500 | E18: 500 | F18: 500 | N18: =SUM(B18:M18) -> 2500
A19: Oleti Viswanath | B19: 0 | C19: 0 | N19: =SUM(B19:M19) -> 0
A20: Thummalapalli Guru Prasanna Lakshmi | B20: 600 | C20: 600 | D20: 600 | E20: 600 | N20: =SUM(B20:M20) -> 2400
A21: Prakash | B21: 0 | C21: 0 | D21: 0 | E21: 0 | F21: 0 | N21: =SUM(B21:M21) -> 0
A22: Panditi Trinath Gupta | B22: 500 | C22: 500 | D22: 500 | E22: 500 | F22: 500 | N22: =SUM(B22:M22) -> 2500
A23: Koppavarapu Sudhakar | B23: 500 | C23: 500 | D23: 500 | F23: 1000 | N23: =SUM(B23:M23) -> 2500
A24: Bank Intrest | B24: 535 | C24: 548 | D24: 647 | E24: 573 | N24: =SUM(B24:M24) -> 2303
A25: Loans Intrest | B25: =1300+650 -> 1950 | C25: =650+1300 -> 1950 | D25: =1300+650 -> 1950 | E25: =1300+650 -> 1950 | F25: =1300+500+650+650 -> 3100 | N25: =SUM(B25:M25) -> 10900
A26: Total | B26: =SUM(B2:B25) -> 9585 | C26: =SUM(C2:C25) -> 9598 | D26: =SUM(D2:D24) -> 7747 | E26: =SUM(E2:E25) -> 7123 | F26: =SUM(F2:F24) -> 10000 | G26: =SUM(G2:G24) -> 0 | H26: =SUM(H1:H24) -> 0 | I26: =SUM(I1:I24) -> 0 | J26: =SUM(J1:J24) -> 0 | K26: =SUM(K1:K24) -> 0 | L26: =SUM(L2:L24) -> 0 | M26: =SUM(M2:M24) -> 0 | N26: =SUM(N2:N24) -> 38203
A28: Summary
A29: Contributions | B29: =SUM(N2:N23) -> 35900
A30: Bank Interest | B30: =SUM(B24:M24) -> 2303
A31: Loans Interest | B31: =SUM(B25:M25) -> 10900

Sheet 2025
A1: Name | B1: Jan | C1: Feb | D1: Mar | E1: Apr | F1: May | G1: Jun | H1: July | I1: Aug | J1: Sep | K1: Oct | L1: Nov | M1: Dec | N1: Total
A2: Kothacheruvu Anil Kumar Reddy | B2: 500 | C2: 500 | D2: 500 | E2: 500 | F2: 500 | G2: 500 | H2: =500+4000 -> 4500 | I2: 500 | J2: 500 | K2: 500 | L2: 500 | M2: 500 | N2: =SUM(B2:M2) -> 10000
A3: Chittiboyina Ramanjaneyulu | B3: 5000 | C3: 1000 | D3: 0 | E3: 0 | F3: 0 | G3: 0 | H3: 0 | K3: 10000 | N3: =SUM(B3:M3) -> 16000
A4: Chintalapalli Srinith | B4: 500 | C4: 500 | D4: 500 | E4: 500 | F4: 500 | G4: 500 | H4: 500 | I4: 500 | J4: 500 | K4: 500 | L4: 500 | M4: 500 | N4: =SUM(B4:M4) -> 6000
A5: Rallabandi Venkata Narasimha Charlu | B5: 500 | C5: 500 | D5: 500 | E5: 500 | F5: 500 | G5: 500 | H5: 500 | I5: 500 | J5: 500 | K5: 500 | L5: 500 | N5: =SUM(B5:M5) -> 5500
A6: Bhagavan Das | B6: 0 | C6: 0 | N6: =SUM(B6:M6) -> 0
A7: Jetty Harikrishna Krishna | B7: 0 | C7: 0 | D7: 0 | E7: 0 | F7: 0 | G7: 0 | H7: 0 | N7: =SUM(B7:M7) -> 0
A8: Darisiguntla Lakshmi Narayana | B8: 500 | C8: 1000 | D8: 500 | E8: 600 | F8: 600 | G8: 500 | H8: 500 | I8: 750 | J8: 750 | K8: 750 | M8: 500 | N8: =SUM(B8:M8) -> 6950
A9: Chindukuri Mallikarjuna | B9: 0 | C9: 0 | D9: 0 | E9: 0 | F9: 500 | G9: 0 | H9: 500 | I9: 0 | J9: 0 | N9: =SUM(B9:M9) -> 1000
A10: Malli Sunil Kumar | B10: 0 | C10: 0 | D10: 0 | E10: 0 | F10: 0 | G10: 0 | H10: 0 | N10: =SUM(B10:M10) -> 0
A11: Korrakuti Paramesh | B11: 500 | C11: 500 | D11: 500 | E11: 500 | F11: 500 | G11: 500 | H11: 500 | I11: 500 | J11: 500 | K11: 500 | L11: 500 | M11: 500 | N11: =SUM(B11:M11) -> 6000
A12: Ponugoti Prasad | B12: 500 | C12: 500 | D12: 500 | E12: 500 | F12: 750 | G12: 770 | H12: 770 | I12: 770 | J12: 750 | K12: 750 | M12: 750 | N12: =SUM(B12:M12) -> 7310
A13: Bollam Samba Siva Reddy | B13: 500 | C13: 500 | D13: 500 | E13: 500 | F13: 0 | G13: 1000 | H13: 500 | I13: 1500 | J13: 500 | K13: =1+1000 -> 1001 | L13: 1000 | N13: =SUM(B13:M13) -> 7501
A14: Biddala Sandeep Kumar Reddy | B14: 500 | C14: 500 | D14: 500 | E14: 500 | F14: 500 | G14: 500 | H14: 500 | I14: 500 | J14: 500 | K14: 500 | L14: 500 | M14: 500 | N14: =SUM(B14:M14) -> 6000
A15: Gopathi Sheshagiri | B15: 0 | C15: 0 | D15: 0 | E15: 0 | F15: 0 | G15: 0 | H15: 0 | N15: =SUM(B15:M15) -> 0
A16: Duggireddy Srinath Reddy | B16: 500 | C16: 500 | D16: 500 | E16: 500 | F16: 500 | G16: 500 | H16: 500 | J16: 500 | K16: 500 | L16: 500 | M16: 1000 | N16: =SUM(B16:M16) -> 6000
A17: Meda Sunil Kumar Reddy | B17: 0 | C17: 0 | D17: 0 | E17: 0 | F17: 0 | G17: 0 | H17: 0 | N17: =SUM(B17:M17) -> 0
A18: Kollai Venkateswarlu | B18: 500 | C18: 500 | E18: 500 | F18: 500 | G18: 500 | H18: 500 | J18: 500 | K18: 500 | L18: 500 | M18: 500 | N18: =SUM(B18:M18) -> 5000
A19: Oleti Viswanath | B19: 0 | C19: 0 | D19: 0 | E19: 0 | F19: 5000 | G19: 0 | H19: 0 | N19: =SUM(B19:M19) -> 5000
A20: Thummalapalli Guru Prasanna Lakshmi | B20: 500 | C20: 500 | D20: 500 | E20: 500 | F20: 500 | G20: 0 | H20: 500 | L20: 600 | M20: 600 | N20: =SUM(B20:M20) -> 4200
A21: Prakash | B21: 0 | C21: 0 | D21: 0 | E21: 0 | F21: 0 | G21: 0 | H21: 0 | N21: =SUM(B21:M21) -> 0
A22: Panditi Trinath Gupta | B22: 1000 | C22: 1000 | D22: 500 | E22: 600 | F22: 0 | G22: 0 | H22: 1800 | I22: 500 | J22: 500 | K22: 500 | L22: 500 | M22: 500 | N22: =SUM(B22:M22) -> 7400
A23: Koppavarapu Sudhakar | B23: 500 | C23: 500 | D23: 500 | E23: 500 | F23: 500 | G23: 500 | H23: 500 | J23: 500 | K23: =500+1 -> 501 | L23: 500 | N23: =SUM(B23:M23) -> 5001
A24: Bank Intrest/M.chit/Loans Intrest | B24: 600 | C24: =600+600 -> 1200 | D24: 600 | G24: 1300 | H24: 1300 | I24: 1300 | J24: 1300 | K24: =1350+1300 -> 2650 | L24: =800 -> 800 | M24: =90+650+1300+174 -> 2214 | N24: =SUM(B24:M24) -> 13264
A25: Total | B25: =SUM(B2:B24) -> 12600 | C25: =SUM(C2:C24) -> 9700 | D25: =SUM(D2:D24) -> 6600 | E25: =SUM(E2:E24) -> 6700 | F25: =SUM(F2:F24) -> 11350 | G25: =SUM(G2:G24) -> 7570 | H25: =SUM(H1:H24) -> 13870 | I25: =SUM(I1:I24) -> 7320 | J25: =SUM(J1:J24) -> 7800 | K25: =SUM(K1:K24) -> 19652 | L25: =SUM(L2:L24) -> 6900 | M25: =SUM(M2:M24) -> 8064 | N25: =SUM(N2:N24) -> 118126

Sheet 2024
A1: Name | B1: Jan | C1: Feb | D1: Mar | E1: Apr | F1: May | G1: Jun | H1: July | I1: Aug | J1: Sep | K1: Oct | L1: Nov | M1: Dec | N1: Total
A2: Kothacheruvu Anil Kumar Reddy | B2: 500 | C2: 500 | D2: 500 | E2: 500 | F2: 500 | G2: 500 | H2: 500 | I2: 500 | J2: 500 | K2: 500 | L2: 500 | M2: 500 | N2: =SUM(B2:M2) -> 6000
A3: Chittiboyina Ramanjaneyulu | F3: 1000 | N3: =SUM(B3:M3) -> 1000
A4: Chintalapalli Srinith | B4: 500 | C4: 500 | D4: 500 | E4: 500 | F4: 500 | G4: 500 | H4: 500 | I4: 500 | J4: 500 | K4: 500 | L4: 500 | M4: 500 | N4: =SUM(B4:M4) -> 6000
A5: Rallabandi Venkata Narasimha Charlu | B5: 500 | C5: 500 | D5: 500 | E5: 500 | F5: 500 | G5: 500 | H5: 500 | J5: 500 | K5: 500 | L5: 500 | M5: 500 | N5: =SUM(B5:M5) -> 5500
A6: Bhagavan Das | N6: =SUM(B6:M6) -> 0
A7: Jetty Harikrishna Krishna | N7: =SUM(B7:M7) -> 0
A8: Darisiguntla Lakshmi Narayana | C8: 1000 | D8: 1000 | G8: 1000 | I8: 500 | N8: =SUM(B8:M8) -> 3500
A9: Chindukuri Mallikarjuna | N9: =SUM(B9:M9) -> 0
A10: Malli Sunil Kumar | N10: =SUM(B10:M10) -> 0
A11: Korrakuti Paramesh | B11: 500 | C11: 500 | D11: 500 | E11: 500 | F11: 500 | G11: 500 | H11: 500 | I11: 500 | J11: 500 | K11: 500 | L11: 500 | M11: 500 | N11: =SUM(B11:M11) -> 6000
A12: Ponugoti Prasad | B12: 500 | C12: 500 | D12: 500 | F12: 500 | H12: 500 | I12: 500 | J12: 500 | K12: 500 | L12: 500 | M12: 500 | N12: =SUM(B12:M12) -> 5000
A13: Bollam Samba Siva Reddy | C13: 500 | D13: 500 | G13: 3300 | I13: 500 | K13: 500 | L13: 500 | M13: 500 | N13: =SUM(B13:M13) -> 6300
A14: Biddala Sandeep Kumar Reddy | B14: 500 | C14: 500 | D14: 500 | E14: 500 | F14: 500 | G14: 500 | H14: 500 | I14: 500 | J14: 500 | K14: 500 | L14: 500 | M14: 500 | N14: =SUM(B14:M14) -> 6000
A15: Gopathi Sheshagiri | N15: =SUM(B15:M15) -> 0
A16: Duggireddy Srinath Reddy | D16: 500 | F16: 500 | G16: 500 | I16: 500 | J16: 500 | K16: 500 | L16: 500 | M16: 500 | N16: =SUM(B16:M16) -> 4000
A17: Meda Sunil Kumar Reddy | N17: =SUM(B17:M17) -> 0
A18: Kollai Venkateswarlu | B18: 500 | D18: 500 | F18: 500 | G18: 500 | H18: 500 | I18: 500 | L18: 500 | M18: 500 | N18: =SUM(B18:M18) -> 4000
A19: Oleti Viswanath | M19: 1000 | N19: =SUM(B19:M19) -> 1000
A20: Thummalapalli Guru Prasanna Lakshmi | B20: 500 | D20: 500 | F20: 500 | I20: 500 | J20: 500 | K20: 500 | L20: 500 | M20: 500 | N20: =SUM(B20:M20) -> 4000
A21: Prakash | N21: =SUM(B21:M21) -> 0
A22: Panditi Trinath Gupta | I22: 1000 | L22: 1500 | N22: =SUM(B22:M22) -> 2500
A23: Koppavarapu Sudhakar | C23: 1000 | D23: 500 | F23: 500 | H23: 500 | I23: 500 | J23: 500 | K23: 500 | L23: 500 | M23: 500 | N23: =SUM(B23:M23) -> 5000
A24: Bank Intrest/M.chit/Loans Intrest | C24: 600 | D24: =5000+600 -> 5600 | G24: 0 | I24: 600 | K24: 600 | L24: 600 | M24: 600 | N24: =SUM(B24:M24) -> 8600
A25: Total | B25: =SUM(B2:B24) -> 4000 | C25: =SUM(C2:C24) -> 6100 | D25: =SUM(D2:D24) -> 12100 | E25: =SUM(E2:E24) -> 2500 | F25: =SUM(F2:F24) -> 6000 | G25: =SUM(G2:G24) -> 7800 | H25: =SUM(H1:H24) -> 4000 | I25: =SUM(I1:I24) -> 7100 | J25: =SUM(J1:J24) -> 4500 | K25: =SUM(K1:K24) -> 5600 | L25: =SUM(L2:L24) -> 7600 | M25: =SUM(M2:M24) -> 7100 | N25: =SUM(N2:N24) -> 74400

Sheet 2023
A1: Name | B1: Jan | C1: Feb | D1: Mar | E1: Apr | F1: May | G1: Jun | H1: July | I1: Aug | J1: Sep | K1: Oct | L1: Nov | M1: Dec | N1: Total
A2: Kothacheruvu Anil Kumar Reddy | K2: 500 | L2: 500 | M2: 500 | N2: =SUM(B2:M2) -> 1500
A3: Chittiboyina Ramanjaneyulu | G3: 3000 | N3: =SUM(B3:M3) -> 3000
A4: Chintalapalli Srinith | B4: 500 | C4: 500 | D4: 500 | F4: 500 | G4: 500 | H4: 500 | I4: 500 | J4: 500 | K4: 500 | L4: 500 | M4: 500 | N4: =SUM(B4:M4) -> 5500
A5: Rallabandi Venkata Narasimha Charlu | E5: 500 | G5: 500 | H5: 500 | I5: 500 | J5: 500 | K5: 500 | L5: 500 | M5: 500 | N5: =SUM(B5:M5) -> 4000
A6: Bhagavan Das | N6: =SUM(B6:M6) -> 0
A7: Jetty Harikrishna Krishna | N7: =SUM(B7:M7) -> 0
A8: Darisiguntla Lakshmi Narayana | C8: 500 | D8: 1000 | E8: 1000 | F8: 500 | G8: 500 | H8: 500 | J8: 500 | K8: 500 | L8: 500 | M8: 500 | N8: =SUM(B8:M8) -> 6000
A9: Chindukuri Mallikarjuna | N9: =SUM(B9:M9) -> 0
A10: Malli Sunil Kumar | N10: =SUM(B10:M10) -> 0
A11: Korrakuti Paramesh | B11: 500 | C11: 500 | D11: 500 | F11: 500 | G11: 500 | H11: 500 | I11: 500 | J11: 500 | K11: 500 | L11: 500 | M11: 500 | N11: =SUM(B11:M11) -> 5500 | R11: 15/03 - 10K credited from Bhagavan Das towards Principal
A12: Ponugoti Prasad | B12: 500 | C12: 500 | D12: 500 | F12: 500 | G12: 500 | H12: 500 | I12: 500 | J12: 500 | K12: 500 | L12: 500 | M12: 500 | N12: =SUM(B12:M12) -> 5500 | R12: 10/04 - 29K credited from GPRS. Need to check the proportion in that.
A13: Bollam Samba Siva Reddy | E13: 500 | G13: 1000 | J13: 500 | L13: 500 | N13: =SUM(B13:M13) -> 2500
A14: Biddala Sandeep Kumar Reddy | B14: 500 | C14: 500 | D14: 500 | F14: 500 | G14: 500 | H14: 500 | I14: 500 | J14: 500 | K14: 500 | L14: 500 | M14: 500 | N14: =SUM(B14:M14) -> 5500
A15: Gopathi Sheshagiri | N15: =SUM(B15:M15) -> 0
A16: Duggireddy Srinath Reddy | B16: 500 | G16: 2500 | K16: 2000 | L16: 500 | M16: 500 | N16: =SUM(B16:M16) -> 6000
A17: Meda Sunil Kumar Reddy | N17: =SUM(B17:M17) -> 0
A18: Kollai Venkateswarlu | B18: 500 | C18: 500 | D18: 500 | G18: 500 | H18: 500 | I18: 500 | J18: 500 | K18: 500 | L18: 500 | M18: 500 | N18: =SUM(B18:M18) -> 5000
A19: Oleti Viswanath | N19: =SUM(B19:M19) -> 0
A20: Thummalapalli Guru Prasanna Lakshmi | C20: 500 | D20: 500 | E20: 500 | F20: 500 | G20: 500 | H20: 500 | I20: 500 | J20: 500 | K20: 500 | L20: 500 | N20: =SUM(B20:M20) -> 5000
A21: Prakash | N21: =SUM(B21:M21) -> 0
A22: Panditi Trinath Gupta | F22: 500 | H22: 500 | J22: 1000 | K22: 1000 | N22: =SUM(B22:M22) -> 3000
A23: Koppavarapu Sudhakar | C23: 500 | F23: 500 | H23: 500 | J23: 500 | M23: 500 | N23: =SUM(B23:M23) -> 2500
A24: Ranga Reddy | F24: 500 | G24: 500 | H24: 500 | K24: 500 | L24: 500 | M24: 500 | N24: =SUM(B24:M24) -> 3000
A25: Bank Intrest/M.chit/Loans Intrest | L25: 600 | N25: =SUM(B25:M25) -> 600
A26: Total | B26: =SUM(B2:B25) -> 3000 | C26: =SUM(C2:C25) -> 4000 | D26: =SUM(D2:D25) -> 4000 | E26: =SUM(E2:E25) -> 2500 | F26: =SUM(F2:F25) -> 4500 | G26: =SUM(G2:G25) -> 11000 | H26: =SUM(H1:H25) -> 5500 | I26: =SUM(I1:I25) -> 3500 | J26: =SUM(J1:J25) -> 6000 | K26: =SUM(K1:K25) -> 8000 | L26: =SUM(L1:L25) -> 6600 | M26: =SUM(M1:M25) -> 5500 | N26: =SUM(N2:N25) -> 64100

Sheet 2022
A1: Name | B1: Jan | C1: Feb | D1: Mar | E1: Apr | F1: May | G1: Jun | H1: July | I1: Aug | J1: Sep | K1: Oct | L1: Nov | M1: Dec | N1: Total
A2: Kothacheruvu Anil Kumar Reddy | B2: 500 | N2: =SUM(B2:M2) -> 500
A3: Chittiboyina Ramanjaneyulu | G3: 1000 | I3: 500 | N3: =SUM(B3:M3) -> 1500
A4: Chintalapalli Srinith | B4: 500 | C4: 500 | D4: 500 | E4: 500 | F4: 500 | G4: 500 | H4: 500 | I4: 500 | J4: 500 | L4: 500 | M4: 500 | N4: =SUM(B4:M4) -> 5500
A5: Rallabandi Venkata Narasimha Charlu | B5: 1000 | C5: 500 | D5: 500 | H5: 500 | N5: =SUM(B5:M5) -> 2500
A6: Bhagavan Das | C6: 500 | D6: 1000 | G6: 1000 | N6: =SUM(B6:M6) -> 2500
A7: Jetty Harikrishna Krishna | N7: =SUM(B7:M7) -> 0
A8: Darisiguntla Lakshmi Narayana | B8: 500 | C8: 500 | D8: 500 | F8: 1000 | G8: 1000 | H8: 1000 | I8: 1000 | J8: 500 | L8: 500 | M8: 500 | N8: =SUM(B8:M8) -> 7000
A9: Chindukuri Mallikarjuna | C9: 500 | D9: 500 | H9: 1000 | N9: =SUM(B9:M9) -> 2000
A10: Malli Sunil Kumar | N10: =SUM(B10:M10) -> 0
A11: Korrakuti Paramesh | B11: 500 | C11: 500 | D11: 500 | E11: 500 | F11: 500 | G11: 500 | H11: 500 | I11: 500 | J11: 500 | L11: 500 | M11: 500 | N11: =SUM(B11:M11) -> 5500
A12: Ponugoti Prasad | B12: 500 | C12: 500 | D12: 500 | E12: 500 | F12: 500 | G12: 500 | H12: 500 | I12: 500 | J12: 500 | L12: 500 | M12: 500 | N12: =SUM(B12:M12) -> 5500
A13: Bollam Samba Siva Reddy | C13: 1000 | D13: 1000 | G13: 1000 | H13: 1000 | I13: 500 | J13: 500 | N13: =SUM(B13:M13) -> 5000
A14: Biddala Sandeep Kumar Reddy | B14: 500 | C14: 500 | D14: 500 | E14: 500 | F14: 500 | G14: 500 | H14: 500 | I14: 500 | J14: 500 | L14: 500 | M14: 500 | N14: =SUM(B14:M14) -> 5500
A15: Gopathi Sheshagiri | N15: =SUM(B15:M15) -> 0
A16: Duggireddy Srinath Reddy | B16: 500 | C16: 500 | D16: 500 | E16: 500 | F16: 500 | G16: 500 | H16: 500 | I16: 500 | J16: 500 | L16: 500 | M16: 500 | N16: =SUM(B16:M16) -> 5500
A17: Meda Sunil Kumar Reddy | D17: 4600 | N17: =SUM(B17:M17) -> 4600
A18: Kollai Venkateswarlu | B18: 500 | C18: 500 | D18: 500 | E18: 500 | F18: 500 | G18: 500 | I18: 500 | J18: 500 | L18: 500 | M18: 500 | N18: =SUM(B18:M18) -> 5000
A19: Oleti Viswanath | B19: 500 | C19: 500 | E19: 1000 | G19: 1000 | N19: =SUM(B19:M19) -> 3000
A20: Thummalapalli Guru Prasanna Lakshmi | B20: 500 | C20: 500 | D20: 500 | E20: 500 | F20: 500 | G20: 500 | H20: 500 | I20: 500 | J20: 500 | L20: 500 | M20: 500 | N20: =SUM(B20:M20) -> 5500
A21: Prakash | N21: =SUM(B21:M21) -> 0
A22: Panditi Trinath Gupta | C22: 1000 | D22: 1000 | J22: 3000 | N22: =SUM(B22:M22) -> 5000
A23: Koppavarapu Sudhakar | B23: 500 | C23: 500 | D23: 500 | F23: 500 | G23: 500 | I23: 500 | J23: 500 | L23: 500 | N23: =SUM(B23:M23) -> 4000
A24: Bank Intrest/M.chit/Loans Intrest | B24: =600+600 -> 1200 | C24: =600+600 -> 1200 | D24: =600+1223 -> 1823 | E24: =600 -> 600 | F24: =600 -> 600 | G24: =600+1500+1689 -> 3789 | H24: =600 -> 600 | I24: 600 | J24: =600+900 -> 1500 | N24: =SUM(B24:M24) -> 11912
A25: Total | B25: =SUM(B2:B24) -> 7700 | C25: =SUM(C2:C24) -> 9700 | D25: =SUM(D2:D24) -> 14923 | E25: =SUM(E2:E24) -> 5100 | F25: =SUM(F2:F24) -> 5600 | G25: =SUM(G2:G24) -> 12789 | H25: =SUM(H1:H24) -> 7100 | N25: =SUM(N2:N24) -> 87512

Sheet 2021
A1: Name | B1: Jan | C1: Feb | D1: Mar | E1: Apr | F1: May | G1: Jun | H1: July | I1: Aug | J1: Sep | K1: Oct | L1: Nov | M1: Dec | N1: Total
A2: Kothacheruvu Anil Kumar Reddy | B2: 500 | C2: 500 | D2: 500 | E2: 500 | I2: 500 | J2: 500 | K2: 500 | L2: 500 | M2: 500 | N2: =SUM(B2:M2) -> 4500
A3: Chittiboyina Ramanjaneyulu | B3: 500 | C3: 500 | D3: 500 | F3: 1000 | H3: 500 | K3: 1000 | M3: 500 | N3: =SUM(B3:M3) -> 4500
A4: Chintalapalli Srinith | B4: 500 | C4: 500 | D4: 500 | E4: 500 | F4: 500 | G4: 500 | H4: 500 | I4: 500 | J4: 500 | K4: 500 | L4: 500 | M4: 500 | N4: =SUM(B4:M4) -> 6000
A5: Rallabandi Venkata Narasimha Charlu | E5: 1000 | F5: 1000 | H5: 1000 | I5: 1000 | K5: 1000 | L5: 1000 | N5: =SUM(B5:M5) -> 6000
A6: Bhagavan Das | C6: 3000 | K6: 2000 | N6: =SUM(B6:M6) -> 5000
A7: Jetty Harikrishna Krishna | N7: =SUM(B7:M7) -> 0
A8: Darisiguntla Lakshmi Narayana | C8: 1000 | E8: 1000 | G8: 800 | H8: 500 | I8: 500 | J8: 500 | K8: 500 | L8: 500 | M8: 500 | N8: =SUM(B8:M8) -> 5800
A9: Chindukuri Mallikarjuna | B9: 1000 | D9: 1000 | F9: 500 | H9: 1000 | I9: 500 | K9: 500 | M9: 1500 | N9: =SUM(B9:M9) -> 6000
A10: Malli Sunil Kumar | N10: =SUM(B10:M10) -> 0
A11: Korrakuti Paramesh | B11: 500 | C11: 500 | D11: 500 | E11: 500 | F11: 500 | G11: 500 | H11: 500 | I11: 500 | J11: 500 | K11: 500 | L11: 500 | M11: 500 | N11: =SUM(B11:M11) -> 6000
A12: Ponugoti Prasad | C12: 1000 | D12: 500 | E12: 500 | F12: 500 | G12: 500 | H12: 500 | I12: 500 | J12: 500 | K12: 500 | L12: 500 | M12: 500 | N12: =SUM(B12:M12) -> 6000
A13: Bollam Samba Siva Reddy | C13: 1000 | N13: =SUM(B13:M13) -> 1000
A14: Biddala Sandeep Kumar Reddy | B14: 500 | C14: 500 | D14: 500 | E14: 500 | F14: 500 | G14: 500 | H14: 500 | I14: 500 | J14: 500 | K14: 500 | L14: 500 | M14: 500 | N14: =SUM(B14:M14) -> 6000
A15: Gopathi Sheshagiri | N15: =SUM(B15:M15) -> 0
A16: Duggireddy Srinath Reddy | C16: 1000 | D16: 500 | E16: 500 | F16: 500 | G16: 500 | H16: 500 | I16: 500 | K16: 1000 | L16: 500 | M16: 500 | N16: =SUM(B16:M16) -> 6000
A17: Meda Sunil Kumar Reddy | E17: 4400 | N17: =SUM(B17:M17) -> 4400
A18: Kollai Venkateswarlu | B18: 500 | C18: 500 | D18: 500 | E18: 500 | F18: 500 | G18: 500 | H18: 500 | I18: 500 | J18: 500 | K18: 500 | L18: 500 | M18: 500 | N18: =SUM(B18:M18) -> 6000
A19: Oleti Viswanath | B19: 1000 | E19: 1000 | F19: 500 | G19: 500 | J19: 1000 | K19: 1000 | M19: 1000 | N19: =SUM(B19:M19) -> 6000
A20: Thummalapalli Guru Prasanna Lakshmi | B20: 1000 | C20: 1000 | D20: 1000 | E20: 1000 | F20: 500 | G20: 500 | H20: 500 | I20: 500 | J20: 500 | K20: 500 | L20: 500 | M20: 500 | N20: =SUM(B20:M20) -> 8000
A21: Prakash | E21: 500 | F21: 500 | H21: 1000 | N21: =SUM(B21:M21) -> 2000
A22: Panditi Trinath Gupta | B22: 500 | C22: 500 | D22: 500 | E22: 500 | F22: 500 | G22: 500 | K22: 2500 | N22: =SUM(B22:M22) -> 5500
A23: Koppavarapu Sudhakar | B23: 1000 | E23: 1000 | H23: 1000 | I23: 1000 | K23: 500 | M23: 500 | N23: =SUM(B23:M23) -> 5000
A24: Bank Intrest/M.chit/Loans Intrest | B24: 666 | C24: =600+2400 -> 3000 | D24: =600+600+1238 -> 2438 | E24: =600+600 -> 1200 | F24: =600 -> 600 | G24: =600+1200+1355 -> 3155 | H24: =600+600 -> 1200 | I24: =600+600 -> 1200 | J24: =600+600+1463 -> 2663 | K24: =600+600 -> 1200 | L24: =600+600 -> 1200 | M24: =600+600+1409 -> 2609 | N24: =SUM(B24:M24) -> 21131
A25: Total | B25: =SUM(B2:B24) -> 8166 | C25: =SUM(C2:C24) -> 14500 | D25: =SUM(D2:D24) -> 8938 | E25: =SUM(E2:E24) -> 15100 | F25: =SUM(F2:F24) -> 8100 | G25: =SUM(G2:G24) -> 8455 | H25: =SUM(H2:H24) -> 9700 | I25: =SUM(I2:I24) -> 8200 | ... N25: =SUM(N2:N24) -> 120831 | O25: =90522-17322 -> 73200

Sheet 2020
A1: Name | B1: Jan | C1: Feb | D1: Mar | E1: Apr | F1: May | G1: Jun | H1: July | I1: Aug | J1: Sep | K1: Oct | L1: Nov | M1: Dec | N1: Total
A2: Kothacheruvu Anil Kumar Reddy | B2: 500 | C2: 500 | D2: 500 | F2: 2000 | K2: 500 | L2: 500 | M2: 1000 | N2: =SUM(B2:M2) -> 5500
A3: Chittiboyina Ramanjaneyulu | E3: 500 | F3: 500 | I3: 1000 | K3: 500 | L3: 1000 | M3: 500 | N3: =SUM(B3:M3) -> 4000
A4: Chintalapalli Srinith | B4: 500 | C4: 500 | D4: 500 | E4: 500 | F4: 500 | G4: 500 | H4: 500 | I4: 500 | J4: 500 | K4: 500 | L4: 500 | M4: 500 | N4: =SUM(B4:M4) -> 6000
A5: Rallabandi Venkata Narasimha Charlu | D5: 500 | F5: 500 | G5: 500 | H5: 1000 | K5: 500 | N5: =SUM(B5:M5) -> 3000
A6: Bhagavan Das | D6: 500 | E6: 500 | F6: 1000 | H6: 2000 | N6: =SUM(B6:M6) -> 4000
A7: Jetty Harikrishna Krishna | H7: 6000 | N7: =SUM(B7:M7) -> 6000
A8: Darisiguntla Lakshmi Narayana | B8: 1000 | D8: 1000 | E8: 1000 | F8: 500 | H8: 1400 | L8: 1000 | M8: 1000 | N8: =SUM(B8:M8) -> 6900
A9: Chindukuri Mallikarjuna | B9: 500 | C9: 500 | D9: 500 | E9: 500 | F9: 500 | I9: 1000 | J9: 500 | K9: 500 | L9: 500 | N9: =SUM(B9:M9) -> 5000
A10: Malli Sunil Kumar | N10: =SUM(B10:M10) -> 0
A11: Korrakuti Paramesh | B11: 500 | C11: 500 | D11: 500 | E11: 500 | F11: 500 | G11: 500 | H11: 500 | I11: 500 | J11: 500 | K11: 500 | L11: 500 | M11: 500 | N11: =SUM(B11:M11) -> 6000
A12: Ponugoti Prasad | D12: 10000 | M12: 2000 | N12: =SUM(B12:M12) -> 12000
A13: Bollam Samba Siva Reddy | B13: 1000 | K13: 1000 | N13: =SUM(B13:M13) -> 2000
A14: Biddala Sandeep Kumar Reddy | B14: 500 | C14: 500 | D14: 500 | E14: 500 | F14: 500 | G14: 500 | H14: 500 | I14: 500 | J14: 500 | K14: 500 | L14: 500 | M14: 500 | N14: =SUM(B14:M14) -> 6000
A15: Gopathi Sheshagiri | N15: =SUM(B15:M15) -> 0
A16: Duggireddy Srinath Reddy | F16: 1000 | H16: 1000 | I16: 500 | J16: 500 | K16: 500 | L16: 500 | M16: 500 | N16: =SUM(B16:M16) -> 4500 | P16: `
A17: Meda Sunil Kumar Reddy | D17: 4000 | H17: 1000 | K17: 2000 | N17: =SUM(B17:M17) -> 7000
A18: Kollai Venkateswarlu | D18: 500 | E18: 500 | F18: 500 | G18: 500 | H18: 500 | I18: 500 | J18: 500 | K18: 500 | L18: 500 | M18: 500 | N18: =SUM(B18:M18) -> 5000
A19: Oleti Viswanath | F19: 5000 | H19: 1000 | J19: 1000 | M19: 1000 | N19: =SUM(B19:M19) -> 8000
A20: Thummalapalli Guru Prasanna Lakshmi | D20: 1000 | E20: 1000 | F20: 1000 | G20: 1000 | H20: 1000 | I20: 1000 | J20: 1000 | K20: 1000 | L20: 1000 | M20: 1000 | N20: =SUM(B20:M20) -> 10000
A21: Prakash | D21: 1000 | E21: 0 | F21: 500 | G21: 500 | H21: 1000 | K21: 500 | L21: 500 | M21: 500 | N21: =SUM(B21:M21) -> 4500
A22: Panditi Trinath Gupta | H22: 1000 | J22: 500 | K22: 505 | L22: 500 | M22: 500 | N22: =SUM(B22:M22) -> 3005
A23: Koppavarapu Sudhakar | M23: 1000 | N23: =SUM(B23:M23) -> 1000
A24: Bank Intrest/M.chit/Loans Intrest | D24: 2243 | G24: 1547 | H24: 3000 | K24: 1752 | M24: 3330 | N24: =SUM(B24:M24) -> 11872
A25: Total | B25: =SUM(B2:B24) -> 4500 | C25: =SUM(C2:C24) -> 2500 | D25: =SUM(D2:D24) -> 23243 | E25: =SUM(E2:E24) -> 5500 | F25: =SUM(F2:F24) -> 14500 | G25: =SUM(G2:G24) -> 5547 | H25: =SUM(H2:H24) -> 21400 | I25: =SUM(I2:I24) -> 5500 | ... N25: =SUM(N2:N24) -> 121277

Sheet 2019
A1: Name | B1: JAN | C1: FEB | D1: MAR | E1: APR | F1: MAY | G1: JUNE | H1: JULY | I1: AUG | J1: SEP | K1: OCT | L1: NOV | M1: DEC | N1: Total
A2: Kothacheruvu Anil Kumar Reddy | B2: 500 | C2: 500 | D2: 500 | E2: 500 | F2: 500 | G2: 500 | H2: 500 | I2: 500 | J2: 500 | K2: 500 | L2: 500 | M2: 500 | N2: =SUM(B2:M2) -> 6000
A3: Chittiboyina Ramanjaneyulu | N3: =SUM(B3:M3) -> 0
A4: Chintalapalli Srinith | B4: 500 | C4: 500 | D4: 500 | E4: 500 | F4: 500 | G4: 500 | H4: 500 | I4: 500 | J4: 500 | K4: 500 | L4: 500 | M4: 500 | N4: =SUM(B4:M4) -> 6000
A5: Rallabandi Venkata Narasimha Charlu | D5: 500 | E5: 500 | F5: 1000 | H5: 500 | K5: 500 | N5: =SUM(B5:M5) -> 3000
A6: Bhagavan Das | N6: =SUM(B6:M6) -> 0
A7: Jetty Harikrishna Krishna | E7: 3000 | N7: =SUM(B7:M7) -> 3000
A8: Darisiguntla Lakshmi Narayana | C8: 500 | E8: 1000 | G8: 1000 | H8: 1000 | L8: 1000 | N8: =SUM(B8:M8) -> 4500
A9: Chindukuri Mallikarjuna | B9: 500 | C9: 500 | D9: 500 | E9: 500 | F9: 500 | G9: 500 | H9: 1000 | J9: 1000 | L9: 1000 | M9: 500 | N9: =SUM(B9:M9) -> 6500
A10: Malli Sunil Kumar | C10: 5000 | N10: =SUM(B10:M10) -> 5000
A11: Korrakuti Paramesh | B11: 500 | C11: 500 | D11: 500 | E11: 500 | F11: 500 | G11: 500 | H11: 500 | I11: 500 | J11: 500 | K11: 500 | L11: 500 | M11: 500 | N11: =SUM(B11:M11) -> 6000
A12: Ponugoti Prasad | N12: =SUM(B12:M12) -> 0
A13: Bollam Samba Siva Reddy | C13: 500 | D13: 500 | L13: 1000 | N13: =SUM(B13:M13) -> 2000
A14: Biddala Sandeep Kumar Reddy | B14: 500 | C14: 500 | D14: 500 | E14: 500 | F14: 500 | G14: 500 | H14: 500 | I14: 500 | J14: 500 | K14: 500 | L14: 500 | M14: 500 | N14: =SUM(B14:M14) -> 6000
A15: Gopathi Sheshagiri | N15: =SUM(B15:M15) -> 0
A16: Duggireddy Srinath Reddy | N16: =SUM(B16:M16) -> 0
A17: Meda Sunil Kumar Reddy | C17: 1000 | D17: 1000 | L17: 3000 | N17: =SUM(B17:M17) -> 5000
A18: Kollai Venkateswarlu | N18: =SUM(B18:M18) -> 0
A19: Oleti Viswanath | N19: =SUM(B19:M19) -> 0
A20: Thummalapalli Guru Prasanna Lakshmi | B20: 0 | C20: 0 | D20: 0 | E20: 0 | F20: 0 | G20: 0 | H20: 0 | I20: 0 | J20: 0 | K20: 0 | L20: 0 | M20: 0 | N20: =SUM(B20:M20) -> 0
A21: Prakash | B21: 0 | C21: 0 | D21: 0 | E21: 0 | F21: 0 | G21: 0 | H21: 0 | I21: 0 | J21: 0 | K21: 0 | L21: 0 | M21: 0 | N21: =SUM(B21:M21) -> 0
A22: Panditi Trinath Gupta | B22: 0 | C22: 0 | D22: 0 | E22: 0 | F22: 0 | G22: 0 | H22: 0 | I22: 0 | J22: 0 | K22: 0 | L22: 0 | M22: 0 | N22: =SUM(B22:M22) -> 0
A23: Koppavarapu Sudhakar | B23: 0 | C23: 0 | D23: 0 | E23: 0 | F23: 0 | G23: 0 | H23: 0 | I23: 0 | J23: 0 | K23: 0 | L23: 0 | M23: 0 | N23: =SUM(B23:M23) -> 0
A24: Bank Intrest/M.chit | C24: 1600 | D24: =1369+800 -> 2169 | G24: 1370 | H24: 4666 | J24: 1813 | L24: 533 | M24: 2052 | N24: =SUM(B24:M24) -> 14203
A25: Total | B25: =SUM(B2:B24) -> 2500 | C25: =SUM(C2:C24) -> 11100 | D25: =SUM(D2:D24) -> 6669 | E25: =SUM(E2:E24) -> 7000 | F25: =SUM(F2:F24) -> 3500 | G25: =SUM(G2:G24) -> 4870 | H25: =SUM(H2:H24) -> 9166 | I25: =SUM(I2:I24) -> 2000 | ... N25: =SUM(N2:N24) -> 67203

Sheet 2018
A1: Name | B1: JAN | C1: FEB | D1: MAR | E1: APR | F1: MAY | G1: JUNE | H1: JULY | I1: AUG | J1: SEP | K1: OCT | L1: NOV | M1: DEC | N1: Total
A2: Kothacheruvu Anil Kumar Reddy | B2: 500 | C2: 500 | D2: 500 | E2: 500 | F2: 500 | G2: 500 | H2: 500 | I2: 500 | J2: 500 | K2: 500 | L2: 500 | M2: 500 | N2: =SUM(B2:M2) -> 6000
A3: Chittiboyina Ramanjaneyulu | B3: 500 | C3: 500 | D3: 1000 | E3: 500 | F3: 500 | G3: 500 | H3: 500 | I3: 500 | N3: =SUM(B3:M3) -> 4500
A4: Chintalapalli Srinith | B4: 1000 | D4: 500 | E4: 500 | F4: 500 | G4: 500 | H4: 500 | I4: 500 | K4: 1000 | M4: 1000 | N4: =SUM(B4:M4) -> 6000
A5: Rallabandi Venkata Narasimha Charlu | B5: 2000 | D5: 2000 | F5: 2000 | H5: 1000 | I5: 1000 | J5: 1000 | K5: 500 | L5: 500 | M5: 500 | N5: =SUM(B5:M5) -> 10500
A6: Bhagavan Das | N6: =SUM(B6:M6) -> 0
A7: Jetty Harikrishna Krishna | C7: 2000 | J7: 3000 | N7: =SUM(B7:M7) -> 5000
A8: Darisiguntla Lakshmi Narayana | B8: 1000 | D8: 2000 | E8: 500 | G8: 1500 | N8: =SUM(B8:M8) -> 5000
A9: Chindukuri Mallikarjuna | B9: 500 | C9: 500 | D9: 500 | F9: 1000 | G9: 500 | H9: 500 | I9: 500 | J9: 500 | K9: 500 | L9: 500 | M9: 500 | N9: =SUM(B9:M9) -> 6000
A10: Malli Sunil Kumar | G10: 3000 | N10: =SUM(B10:M10) -> 3000
A11: Korrakuti Paramesh | B11: 1000 | D11: 500 | E11: 500 | F11: 500 | G11: 500 | H11: 500 | I11: 500 | K11: 1000 | M11: 1000 | N11: =SUM(B11:M11) -> 6000
A12: Ponugoti Prasad | B12: 500 | E12: 2000 | G12: 500 | H12: 1000 | M12: 2000 | N12: =SUM(B12:M12) -> 6000
A13: Bollam Samba Siva Reddy | B13: 500 | C13: 500 | D13: 500 | E13: 500 | F13: 500 | H13: 500 | I13: 500 | K13: 1000 | L13: 500 | M13: 500 | N13: =SUM(B13:M13) -> 5500
A14: Biddala Sandeep Kumar Reddy | B14: 1000 | D14: 500 | E14: 500 | F14: 500 | G14: 500 | H14: 500 | I14: 500 | K14: 1000 | M14: 1000 | N14: =SUM(B14:M14) -> 6000
A15: Gopathi Sheshagiri | N15: =SUM(B15:M15) -> 0
A16: Duggireddy Srinath Reddy | B16: 500 | C16: 500 | D16: 1000 | E16: 500 | F16: 500 | G16: 500 | H16: 500 | I16: 500 | N16: =SUM(B16:M16) -> 4500
A17: Meda Sunil Kumar Reddy | B17: 4000 | K17: 4000 | L17: 1000 | M17: 500 | N17: =SUM(B17:M17) -> 9500
A18: Kollai Venkateswarlu | B18: 500 | C18: 500 | D18: 500 | E18: 500 | G18: 1000 | H18: 500 | I18: 500 | J18: 500 | K18: 500 | L18: 500 | N18: =SUM(B18:M18) -> 5500
A19: Oleti Viswanath | B19: 2000 | C19: 1000 | H19: 2000 | N19: =SUM(B19:M19) -> 5000
A20: Thummalapalli Guru Prasanna Lakshmi | B20: 0 | C20: 0 | D20: 0 | E20: 0 | F20: 0 | G20: 0 | H20: 0 | I20: 0 | J20: 0 | K20: 0 | L20: 0 | M20: 0 | N20: =SUM(B20:M20) -> 0
A21: Prakash | B21: 0 | C21: 0 | D21: 0 | E21: 0 | F21: 0 | G21: 0 | H21: 0 | I21: 0 | J21: 0 | K21: 0 | L21: 0 | M21: 0 | N21: =SUM(B21:M21) -> 0
A22: Panditi Trinath Gupta | B22: 0 | C22: 0 | D22: 0 | E22: 0 | F22: 0 | G22: 0 | H22: 0 | I22: 0 | J22: 0 | K22: 0 | L22: 0 | M22: 0 | N22: =SUM(B22:M22) -> 0
A23: Koppavarapu Sudhakar | B23: 0 | C23: 0 | D23: 0 | E23: 0 | F23: 0 | G23: 0 | H23: 0 | I23: 0 | J23: 0 | K23: 0 | L23: 0 | M23: 0 | N23: =SUM(B23:M23) -> 0
A24: Bank Intrest/M.chit | B24: 1612 | D24: 402 | E24: 11458 | G24: 2018 | J24: 2135 | M24: =1563+800 -> 2363 | N24: =SUM(B24:M24) -> 19988
A25: Total | B25: =SUM(B2:B24) -> 17112 | C25: =SUM(C2:C24) -> 6000 | D25: =SUM(D2:D24) -> 9902 | E25: =SUM(E2:E24) -> 17958 | F25: =SUM(F2:F24) -> 6500 | G25: =SUM(G2:G24) -> 11518 | H25: =SUM(H2:H24) -> 8500 | I25: =SUM(I2:I24) -> 5500 | ... N25: =SUM(N2:N24) -> 113988

Sheet 2017
A1: Name | B1: JAN | C1: FEB | D1: MAR | E1: APR | F1: MAY | G1: JUNE | H1: JULY | I1: AUG | J1: SEP | K1: OCT | L1: NOV | M1: DEC | N1: Total
A2: Kothacheruvu Anil Kumar Reddy | B2: 2000 | C2: 500 | D2: 500 | E2: 1000 | F2: 500 | G2: 500 | H2: 500 | J2: 2000 | L2: 500 | M2: 500 | N2: =SUM(B2:M2) -> 8500
A3: Chittiboyina Ramanjaneyulu | B3: 500 | C3: 500 | D3: 500 | E3: 500 | F3: 500 | G3: 500 | H3: 500 | I3: 500 | J3: 500 | K3: 500 | L3: 500 | M3: 500 | N3: =SUM(B3:M3) -> 6000
A4: Chintalapalli Srinith | D4: 2000 | G4: 2000 | K4: 1000 | L4: 500 | M4: 500 | N4: =SUM(B4:M4) -> 6000
A5: Rallabandi Venkata Narasimha Charlu | B5: 1500 | C5: 1000 | D5: 500 | E5: 1000 | F5: 1000 | G5: 1000 | H5: 1000 | I5: 1000 | J5: 1000 | K5: 1000 | L5: 1000 | N5: =SUM(B5:M5) -> 11000
A6: Bhagavan Das | D6: 3000 | N6: =SUM(B6:M6) -> 3000
A7: Jetty Harikrishna Krishna | C7: 2500 | H7: 3000 | J7: 500 | K7: 1000 | L7: 2000 | N7: =SUM(B7:M7) -> 9000
A8: Darisiguntla Lakshmi Narayana | B8: 500 | C8: 500 | D8: 500 | E8: 500 | F8: 500 | G8: 500 | H8: 500 | N8: =SUM(B8:M8) -> 3500
A9: Chindukuri Mallikarjuna | B9: 500 | C9: 500 | D9: 500 | E9: 500 | F9: 550 | G9: 500 | H9: 500 | I9: 500 | K9: 1000 | M9: 1000 | N9: =SUM(B9:M9) -> 6050
A10: Malli Sunil Kumar | E10: 1000 | K10: 1000 | L10: 2000 | N10: =SUM(B10:M10) -> 4000
A11: Korrakuti Paramesh | B11: 1000 | D11: 500 | E11: 500 | G11: 1500 | I11: 1000 | K11: 500 | L11: 500 | M11: 500 | N11: =SUM(B11:M11) -> 6000
A12: Ponugoti Prasad | B12: 500 | C12: 500 | D12: 500 | E12: 500 | F12: 500 | G12: 500 | H12: 500 | I12: 1000 | K12: 1000 | M12: 500 | N12: =SUM(B12:M12) -> 6000
A13: Bollam Samba Siva Reddy | B13: 500 | C13: 500 | D13: 500 | E13: 500 | F13: 500 | G13: 500 | H13: 500 | I13: 500 | J13: 500 | K13: 500 | L13: 500 | M13: 500 | N13: =SUM(B13:M13) -> 6000
A14: Biddala Sandeep Kumar Reddy | B14: 1000 | C14: 500 | D14: 500 | E14: 500 | G14: 1500 | I14: 1000 | K14: 500 | L14: 500 | M14: 500 | N14: =SUM(B14:M14) -> 6500
A15: Gopathi Sheshagiri | B15: 1000 | C15: 1000 | H15: 2000 | L15: 2000 | N15: =SUM(B15:M15) -> 6000
A16: Duggireddy Sreenadh Reddy | B16: 500 | C16: 500 | D16: 500 | E16: 500 | F16: 500 | G16: 500 | H16: 500 | I16: 500 | J16: 500 | K16: 500 | L16: 500 | M16: 500 | N16: =SUM(B16:M16) -> 6000
A17: Meda Sunil Kumar Reddy | B17: 500 | G17: 2000 | N17: =SUM(B17:M17) -> 2500
A18: Kollai Venkateswarlu | C18: 500 | D18: 500 | E18: 500 | F18: 500 | G18: 500 | H18: 500 | J18: 1000 | K18: 500 | L18: 500 | M18: 500 | N18: =SUM(B18:M18) -> 5500
A19: Oleti Viswanath | B19: 1000 | C19: 1000 | D19: 500 | E19: 500 | G19: 1000 | H19: 1000 | J19: 1000 | N19: =SUM(B19:M19) -> 6000
A20: Thummalapalli Guru Prasanna Lakshmi | B20: 0 | C20: 0 | D20: 0 | E20: 0 | F20: 0 | G20: 0 | H20: 0 | I20: 0 | J20: 0 | K20: 0 | L20: 0 | M20: 0 | N20: =SUM(B20:M20) -> 0
A21: Prakash | B21: 0 | C21: 0 | D21: 0 | E21: 0 | F21: 0 | G21: 0 | H21: 0 | I21: 0 | J21: 0 | K21: 0 | L21: 0 | M21: 0 | N21: =SUM(B21:M21) -> 0
A22: Panditi Trinath Gupta | B22: 0 | C22: 0 | D22: 0 | E22: 0 | F22: 0 | G22: 0 | H22: 0 | I22: 0 | J22: 0 | K22: 0 | L22: 0 | M22: 0 | N22: =SUM(B22:M22) -> 0
A23: Koppavarapu Sudhakar | B23: 0 | C23: 0 | D23: 0 | E23: 0 | F23: 0 | G23: 0 | H23: 0 | I23: 0 | J23: 0 | K23: 0 | L23: 0 | M23: 0 | N23: =SUM(B23:M23) -> 0
A24: Bank Intrest/M.chit | D24: 500 | G24: 428 | H24: 2042 | J24: 368 | M24: 135 | N24: =SUM(B24:M24) -> 3473
A25: Total | B25: =SUM(B2:B24) -> 11000 | C25: =SUM(C2:C24) -> 10000 | D25: =SUM(D2:D24) -> 11500 | E25: =SUM(E2:E24) -> 8000 | F25: =SUM(F2:F24) -> 5050 | G25: =SUM(G2:G24) -> 13428 | H25: =SUM(H2:H24) -> 13042 | I25: =SUM(I2:I24) -> 6000 | ... N25: =SUM(N2:N24) -> 111023

Sheet 2016
A1: Name | B1: July | C1: Aug | D1: Sep | E1: Oct | F1: Nov | G1: Dec | H1: Total-2016
A2: Kothacheruvu Anil Kumar Reddy | B2: 2000 | E2: 500 | F2: 500 | G2: 5000 | H2: =SUM(B2:G2) -> 8000
A3: Chittiboyina Ramanjaneyulu | C3: 2000 | E3: 500 | F3: 500 | G3: 500 | H3: =SUM(B3:G3) -> 3500
A4: Chintalapalli Srinith | C4: 2000 | E4: 500 | F4: 500 | G4: 500 | H4: =SUM(B4:G4) -> 3500
A5: Rallabandi Venkata Narasimha Charlu | B5: 1300 | C5: 700 | D5: 500 | F5: 500 | G5: 1000 | H5: =SUM(B5:G5) -> 4000
A6: Bhagavan Das | C6: 3000 | E6: 3000 | H6: =SUM(B6:G6) -> 6000
A7: Jetty Harikrishna Krishna | D7: 2000 | E7: 500 | G7: 2000 | H7: =SUM(B7:G7) -> 4500
A8: Darisiguntla Lakshmi Narayana | C8: 2000 | E8: 500 | F8: 2000 | G8: 500 | H8: =SUM(B8:G8) -> 5000
A9: Chindukuri Mallikarjuna | B9: 200 | E9: 2300 | F9: 500 | G9: 500 | H9: =SUM(B9:G9) -> 3500
A10: Malli Sunil Kumar | C10: 2000 | G10: 2000 | H10: =SUM(B10:G10) -> 4000
A11: Korrakuti Paramesh | B11: 2000 | E11: 500 | F11: 500 | G11: 500 | H11: =SUM(B11:G11) -> 3500
A12: Ponugoti Prasad | B12: 2000 | E12: 500 | F12: 500 | G12: 500 | H12: =SUM(B12:G12) -> 3500
A13: Bollam Samba Siva Reddy | D13: 2000 | E13: 500 | F13: 500 | G13: 500 | H13: =SUM(B13:G13) -> 3500
A14: Biddala Sandeep Kumar Reddy | E14: 3500 | F14: 500 | H14: =SUM(B14:G14) -> 4000
A15: Gopathi Sheshagiri | B15: 2000 | F15: 1000 | H15: =SUM(B15:G15) -> 3000
A16: Duggireddy Srinath Reddy | C16: 2000 | E16: 500 | F16: 500 | G16: 500 | H16: =SUM(B16:G16) -> 3500
A17: Meda Sunil Kumar Reddy | D17: 2500 | F17: 1000 | H17: =SUM(B17:G17) -> 3500
A18: Kollai Venkateswarlu | C18: 2000 | E18: 2000 | H18: =SUM(B18:G18) -> 4000
A19: Oleti Viswanath | E19: 2500 | F19: 500 | G19: 500 | H19: =SUM(B19:G19) -> 3500
A20: Thummalapalli Guru Prasanna Lakshmi | B20: 0 | C20: 0 | D20: 0 | E20: 0 | F20: 0 | G20: 0 | H20: =SUM(B20:G20) -> 0
A21: Prakash | B21: 0 | C21: 0 | D21: 0 | E21: 0 | F21: 0 | G21: 0 | H21: =SUM(B21:G21) -> 0
A22: Panditi Trinath Gupta | B22: 0 | C22: 0 | D22: 0 | E22: 0 | F22: 0 | G22: 0 | H22: =SUM(B22:G22) -> 0
A23: Koppavarapu Sudhakar | B23: 0 | C23: 0 | D23: 0 | E23: 0 | F23: 0 | G23: 0 | H23: =SUM(B23:G23) -> 0
A24: Bank Intrest/M.chit | B24: 9 | E24: 311 | G24: 384 | H24: =SUM(B24:G24) -> 704
A25: Total | H25: =SUM(H2:H24) -> 74704

Sheet New_Resolutions_27-07-20
A1: Date | B1: 27-07-2020
A2: Attendees | B2: Mallikarjuna C, Seshagiri G, Bhagvan Das, Prasad P, Anil K, Sreenath CH, Sreenath reddy, Sunil Kumar Reddy, M Sunil Kumar, Samba B, O Viswanath, Sandeep B, Paramesh K, J Hari Krishna, Chari VN, Lakshmi Narayana
A3: Non Attendees | B3: Prakash P, Anji, Venkateswarulu Trinath, Guru Prasanna Lakshmi (New members)
A5: General notes | B5: 1. We all thank Malli C for holding this group together by his tremendous efforts and good will. 2. We all need to commend ourselves for running this group steadfastly for 4 years. There are highs and lows but we all agree that it's still a great achievement. 3. We regret that we were not able to act on one of the requests timely and decided not to repeat this again. 4. We all are friends in first place and this is a place to help each other out. Feel free to discuss any financial necessities like loans with whomever is your closest SPOC/member. 5. To encourage other AITS friends to join FCF by reaching out to them. 6. Helping non FCF members came up and we decided member closer to them can reach out to them and encourage to come up with a plan.
A7: Below are the resolutions as per our 27/Jul/2020 Zoom meeting | D7: C.Mallikarjuna | E7: Paramesh
A8: S.No. | B8: Resolution | C8: Member responsible | D8: opinion | E8: Confirmation
A9: 1 | B9: The distinction as Refundable/Non Refundable members is discontinued. | C9: All | D9: Need to discuss on this in forth coming FCF conference. | E9: This has been agreed by all the people in the meeting. Still there is an option to decide at the end rather than declaring at initial.
A10: 2 | B10: Members will be allowed to decide whether they want their contributions back or donate to any charity at the time of leaving or closure of FCF. | C10: All | D10: ok
A11: 3 | B11: Contribution refunds will be minus any member's contribution towards bad debts/expenses/social contributions | C11: All | D11: ok
A12: 4 | B12: We will try to register as a trust if its feasible. Malli to look into the details and call out for any help required from members | C12: Malli C | D12: ok
A13: 5 | B13: The immediate help for health reasons is still confined to immediate family members(Parents, Spouse & Children) but members are actively encouraged to reach out for help if any others(siblings/in laws etc) need financial help for health reasons. We will use Social fund for this and where this might not be possible might consider an exception on members agreement. | C13: All | D13: ok
A14: 6 | B14: Members are encouraged to seek out actively for any loans if they have any financial necessities. Members should understand we will decide based on the financial reserves at the time. | C14: All | D14: ok
A15: 7 | B15: Social help will continue based on a quarterly budget basis of 25k. Please flag any requests as soon as you can to allow enough time for all the members to respond. | C15: All | D15: Based on past history of donations..we did not cross 35k per anuum.social help 25k Per Quarter may not possible. So my opinion is need to make change in that. | E15: We can keep 10K per quarter. Can carry forward the amount, if past quarter not utilised.
A16: 8 | B16: We will try to change the account to a joint account and try to share the credentials on a rotation basis so that Malli alone is not burdened to manage the entire financial book keeping. | C16: Malli C | D16: ok
A17: 9 | B17: Clarification that we will continue to contribute to FCF as there was a confusion that we dont need to contribute once corpus fund is reached. | C17: All | D17: we decided (in conference meeting )that we will come to some clarity over this in forth coming FCF meetings. After that only we will figure out corpus fund value with the all members acceptance.
A18: 10 | B18: To have quarterly/half yearly catchups to discuss our status and consider any improvements to the previous resolutions. | C18: Anil | D18: ok
B24: General Rules (2023 Meet)
B25: - Raise Fixed Corpus Fund to ₹5L, with yearly 20% increments or depends on inflation.
B26: - Personal loans are not feasible to offer until the principal reaches the fixed corpus, except for medical loans.
B27: - Increase the monthly contributions from ₹500 to ₹600, with an annual review to adjust for inflation, while also considering everyone's financial circumstances.
B28: - Increase personal loan interest rate from 6% to 8%. This ensures more professional and sustainable fund management, primarily maintained for friends. Note that those taking loans contribute to the fund, fostering shared responsibility and mutual support.
B29: - Current: ₹600/- for 1 Lakh
B30: - New: ₹650/- for 1 Lakh
B31: - Personal loan tenure should not exceed 6 months, unless there are exceptional circumstances such as natural disasters, job loss, or other significant hardships. This ensures the fund can benefit all contributors, who are in need rather than being tied up in long-term loans by a single member.
B32: - Identify individuals who are not actively contributing and request them to match the actual contributions gradually over a period of 6 months to help raise the fund.
B33: - Calculate TDS to pay to Govt from interest and other earnings from the fund and adjust in the principal.
